<compatibility-matrix version="1.0" type="framework">
    <hal format="hidl" optional="true">
        <name>android.hardware.bluetooth</name>
        <version>1.0</version>
    </hal>
    <hal format="hidl" optional="true">
        <name>android.hardware.boot</name>
        <version>1.0</version>
    </hal>
    <hal format="hidl" optional="true">
        <name>android.hardware.configstore</name>
        <version>1.0</version>
    </hal>
    <hal format="hidl" optional="true">
        <name>android.hardware.ir</name>
        <version>1.0</version>
    </hal>
    <hal format="hidl" optional="true">
        <name>android.hardware.nfc</name>
        <version>1.0</version>
    </hal>
    <hal format="hidl" optional="true">
        <name>android.hardware.radio</name>
        <version>1.0</version>
    </hal>
    <hal format="hidl" optional="true">
        <name>android.hardware.renderscript</name>
        <version>1.0</version>
    </hal>
    <hal format="hidl" optional="true">
        <name>android.hardware.wifi</name>
        <version>1.0</version>
    </hal>
</compatibility-matrix>
